{	
	"borts": {
		"0": {"title": "класичний",
			"price": 0}, 
		"1": {"title": "сирний",
			"price": 50}, 
		"2": {"title": "ковбасний",
			"price": 50}
	},
	
	"catOfIngred":{
		"1": "Тісто",
		"2": "М'ясо",
		"3": "Риба",
		"4": "Овочі",
		"8": "Сири",
		"7": "Соуси"
	},
	"ingr":{
		"1": ["Тісто для піци", 0],
		"2": ["Бекон", 14],
		"21": ["Запечена курочка", 12],
		"22": ["Копчена курочка",  12],
		"23": ["Пепероні", 25],
		"24": ["Салямі", 17],
		"25": ["Мисливські ковбаски", 15],
		"26": ["Шинка", 16],
		"3": ["Лосось", 0],
		"31": ["Тунець", 0],
		"433": ["Томати", 10],
		"41": ["Кукурудза", 8],
		"42": ["Оливки", 8],
		"43": ["Солодкий перець", 10],
		"44": ["Гострий Джалапено", 10],
		"45": ["Мариновані гриби", 10],
		"46": ["Маринована цибуля", 8],
		"48": ["Свіжі гриби", 8],
	   	"49": ["Мариновані огірки", 10],
		"411":[ "Ананас", 28],
		"422": ["Кунжут", 5],
		"7": ["Соус 'Барбекю'", 10],
		"71": ["Американська гірчиця", 6],
		"72": ["Соус 'Бургер'", 8],
		"73": ["Соус 'Солодкий Чилі'", 10],
		"75":[ "Червоний соус", 10],
		"76":[ "Білий соус", 10],
		"81": ["Моцарела, Гауда", 20],
		"82": ["Блю Чіз", 36],
		"83": ["Пармезан", 42],
		"84": ["Фета", 13]
	},


	"pizzas": [{
			"id": 1,
			"img": "https://m2t.pizza/img/ferd.png",
			"name": "Ферджі",
			"price": 165,
			"descr": [
				"75", "81", "26","22","43","45","433", "73"],
			"category": ["new"],
			"calories": 1401,
			"satiety": "1-2",
			"rating": 10,
			"weight": "650 г"
		},
		{
			"id": 2,
			"img": "https://m2t.pizza/img/4meat.png",
			"name": "4 м'яса",
			"price": 155,
			"descr": [
				"75", "81", "24","21","2","25","433","48"],
			"category": ["hit"],
			"calories": 1617,
			"feature": [],
			"satiety": "1-2",
			"rating": 10,
			"weight": "625 г"
		},
		{
			"id": 3,
			"img": "https://m2t.pizza/img/4syr.png",
			"name": "4 сири",
			"price": 170,
			"descr": [
				"76", "81", "83", "82"],
			"category": ["vegan"],
			"calories": 1712,
			"satiety": "1-2",
			"rating": 5,
			"weight": "600 г"
		},
		{
			"id": 4,
			"img": "https://m2t.pizza/img/lakto-vegan.png",
			"name": "Лакто-Веган",
			"price": 135,
			"descr": [
				"75", "81", "42","43","433","48", "84"],
			"category": ["vegan"],
			"calories": 1221,
			"satiety": "1-2",
			"rating": 2,
			"weight": "610 г"
		},
		{
			"id": 5,
			"img": "https://m2t.pizza/img/margo.png",
			"name": "Маргарита",
			"price": 135,
			"descr": ["75", "81", "433", "83"],
			"category": ["vegan"],
			"calories": 1286,
			"satiety": "1-2",
			"rating": 4,
			"weight": "530 г"
		},
		{
			"id": 6,
			"img": "https://m2t.pizza/img/grib.png",
			"name": "Грибная",
			"price": 145,
			"descr": ["76", "81", "21", "48", "83"], 
			"category": [],
			"calories": 1288,
			"satiety": "1-2",
			"rating": 2,
			"weight": "585 г"
		},
		{
			"id": 7,
			"img": "https://m2t.pizza/img/mak.png",
			"name": "МакДональдз",
			"price": 160,
			"descr": [
				"75", "81", "2", "433", "46","49","72", "71", "422"],
			"category": [],
			"calories": 5800,
			"satiety": "1-2",
			"rating": 5,
			"weight": "645 г"
		},
		{
			"id": 8,
			"img": "https://m2t.pizza/img/4sez.png",
			"name": "4 Сезони",
			"price": 165,
			"descr": [
				"75", "76", "81", "433", "25", "49", "48", "23", "22", "41", "45", "21", "83"],
			"category": ["hit"],
			"calories": 1370,
			"satiety": "1-2",
			"rating": 10,
			"weight": "600 г"
		},
		{
			"id": 9,
			"img": "https://m2t.pizza/img/bbq.png",
			"name": "Барбекю",
			"price": 165,
			"descr": [
				"75", "81", "2", "46", "43", "433", "7"],
			"category": [],
			"calories": 1892,
			"satiety": "1-2",
			"rating": 8,
			"weight": "600 г"
		},
		{
			"id": 10,
			"img": "https://m2t.pizza/img/gavai.png",
			"name": "Гавайська",
			"price": 165,
			"descr": [
				"75", "81", "21", "433", "41", "411"],
			"category": [],
			"calories": 1251,
			"satiety": "1-2",
			"rating": 7,
			"weight": "650 г"
		},
		{
			"id": 11,
			"img": "https://m2t.pizza/img/tiamo.png",
			"name": "Тіамо",
			"price": 165,
			"descr": [
				"76", "81", "433", "49", "48", "2", "22", "422", "72"],
			"category": ["hit"],
			"calories": 1700,
			"satiety": "1-2",
			"rating": 10,
			"weight": "650 г"
		},
		{
			"id": 12,
			"img": "https://m2t.pizza/img/californ.png",
			"name": "Каліфорнія",
			"price": 155,
			"descr": [
				"75", "81", "41", "22", "45", "433"],
			"category": ["hit"],
			"calories": 1230,
			"satiety": "1-2",
			"rating": 10,
			"weight": "630 г"
		},
		{
			"id": 13,
			"img": "https://m2t.pizza/img/bona.png",
			"name": "Бона",
			"price": 155,
			"descr": [
				"75", "81", "22", "2", "46", "433", "84"],
			"category": [],
			"calories": 1583,
			"satiety": "1-2",
			"rating": 2,
			"weight": "620 г"
		},
		{
			"id": 14,
			"img": "https://m2t.pizza/img/hunter.png",
			"name": "Хантер",
			"price": 165,
			"descr": [
				"75", "81", "433", "45", "48", "25"],
			"category": [],
			"calories": 1487,
			"satiety": "1-2",
			"rating": 6,
			"weight": "645 г"
		},
		{
			"id": 15,
			"img": "https://m2t.pizza/img/astra.png",
			"name": "Астра",
			"price": 165,
			"descr": [
				"75", "81", "433", "24", "25", "43", "44"],
			"category": ["hot"],
			"calories": 1530,
			"satiety": "1-2",
			"rating": 5,
			"weight": "625 г"
		},
		{
			"id": 16,
			"img": "https://m2t.pizza/img/peperoni.png",
			"name": "Пепероні",
			"price": 155,
			"descr": [
				"75", "81", "23"],
			"category": [],
			"calories": 1597,
			"satiety": "1-2",
			"rating": 5,
			"weight": "540 г"
		},
		{
			"id": 17,
			"img": "https://m2t.pizza/img/gret.png",
			"name": "Грета",
			"price": 165,
			"descr": [
				"76", "81", "433", "48", "26", "43", "72"],
			"category": ["hit"],
			"calories": 1538,
			"satiety": "1-2",
			"rating": 5,
			"weight": "650 г"
		},
		{
			"id": 18,
			"img": "https://m2t.pizza/img/kapr.png",
			"name": "Капрічоза",
			"price": 145,
			"descr": [
				"75", "81", "26", "48", "42"],
			"category": [],
			"calories": 1348,
			"satiety": "1-2",
			"rating": 1,
			"weight": "580 г"
		}
	]

}
